[{"path": "La Aficion", "type": "file", "name": "CRUZ AZUL 170914 (6)_", "modifiedDate": "2014-09-17T15:19:00"}, {"path": "La Aficion", "type": "file", "name": "CRUZ AZUL 170914 (5)_", "modifiedDate": "2014-09-17T15:19:00"}, {"path": "La Aficion", "type": "file", "name": "CRUZ AZUL 170914 (1)_", "modifiedDate": "2014-09-17T15:07:00"}, {"path": "La Aficion", "type": "file", "name": "CRUZ AZUL 170914 (2)_", "modifiedDate": "2014-09-17T15:07:00"}, {"path": "La Aficion", "type": "file", "name": "CRUZ AZUL 170914 (4)_", "modifiedDate": "2014-09-17T15:06:00"}, {"path": "La Aficion", "type": "file", "name": "CRUZ AZUL 170914 (3)_", "modifiedDate": "2014-09-17T15:06:00"}, {"path": "Internacionales", "type": "file", "name": "obamairak_", "modifiedDate": "2014-09-17T14:53:00"}, {"path": "Internacionales", "type": "file", "name": "cameronbite_", "modifiedDate": "2014-09-17T12:38:00"}, {"path": "Internacionales", "type": "file", "name": "escocia17_", "modifiedDate": "2014-09-17T11:12:00"}, {"path": "Internacionales", "type": "file", "name": "airfrance_", "modifiedDate": "2014-09-17T11:00:00"}, {"path": "Internacionales", "type": "file", "name": "empresarioruso_", "modifiedDate": "2014-09-17T08:22:00"}, {"path": "Internacionales", "type": "file", "name": "niniosiria_", "modifiedDate": "2014-09-17T08:21:00"}, {"path": "SKY", "type": "file", "name": "tvc 2pm_9-17-2014", "modifiedDate": "2014-09-17T14:02:00"}, {"path": "Estados", "type": "file", "name": "UPDATEAFECTACIONESLLUVIASTMPS2 (2)_", "modifiedDate": "2014-09-17T10:53:00"}, {"path": "Estados", "type": "file", "name": "UPDATEAFECTACIONESLLUVIASTMPS4_", "modifiedDate": "2014-09-17T10:35:00"}, {"path": "Estados", "type": "file", "name": "UPDATEAFECTACIONESLLUVIASTMPS_", "modifiedDate": "2014-09-17T10:09:00"}, {"path": "Estados", "type": "file", "name": "UPDATEAFECTACIONESLLUVIASTMPS3_", "modifiedDate": "2014-09-17T10:09:00"}, {"path": "Monterrey", "type": "file", "name": "INFORME MANCERA DF BITE", "modifiedDate": "2014-09-17T15:18:00"}, {"path": "Monterrey", "type": "file", "name": "INFORME MANCERA DF VO", "modifiedDate": "2014-09-17T15:13:00"}, {"path": "Monterrey", "type": "file", "name": "MILEY CIRUS CONCIERTO MTY", "modifiedDate": "2014-09-17T15:00:00"}, {"path": "Monterrey", "type": "file", "name": "JOSE LUIS GARZA INTERJET AUDIO", "modifiedDate": "2014-09-17T14:43:00"}, {"path": "Monterrey", "type": "file", "name": "MILEY CIRUS BANDERA MEX VO", "modifiedDate": "2014-09-17T14:33:00"}]